iotbit_library/__init__.py
iotbit_library/iotmodem.py
iotbit_library-1.0.6.dist-info/METADATA
iotbit_library-1.0.6.dist-info/WHEEL
iotbit_library-1.0.6.dist-info/top_level.txt
iotbit_library-1.0.6.dist-info/RECORD
