Metadata-Version: 2.1
Name: iotbit-library
Version: 1.0.6
Summary: Library to work with the IoTBit Industrial version on the Raspberry Pi
Home-page: UNKNOWN
Author: Sam
Author-email: sam@altitude.pw
License: UNKNOWN
Platform: UNKNOWN
Classifier: Programming Language :: Python :: 3
Classifier: Operating System :: POSIX :: Linux
Classifier: Development Status :: 5 - Production/Stable 
Requires-Dist: pyserial
Requires-Dist: RPI.GPIO
